LICENCE.txt
MANIFEST.in
README.rst
setup.py
confirmanager/__init__.py
confirmanager/factories.py
confirmanager/models.py
confirmanager/signals.py
confirmanager/tests.py
confirmanager/urls.py
confirmanager/utils.py
confirmanager/views.py
confirmanager/locale/ru/LC_MESSAGES/django.mo
confirmanager/locale/ru/LC_MESSAGES/django.po
confirmanager/migrations/0001_initial.py
confirmanager/migrations/__init__.py
confirmanager/templates/confirmanager/confirmation.html
confirmanager/templatetags/__init__.py
confirmanager/templatetags/confirmation_utils.py
django_confirmanager.egg-info/PKG-INFO
django_confirmanager.egg-info/SOURCES.txt
django_confirmanager.egg-info/dependency_links.txt
django_confirmanager.egg-info/requires.txt
django_confirmanager.egg-info/top_level.txt
test_app/__init__.py
test_app/test_settings.py
test_app/urls.py