Metadata-Version: 1.1
Name: django-confirmanager
Version: 0.4
Summary: Simple email confirmation application.
Home-page: https://github.com/futurecolors/django-confirmanager
Author: Ilya Baryshev
Author-email: baryshev@gmail.com
License: MIT
Platform: UNKNOWN
Classifier: Development Status :: 3 - Alpha
Classifier: Framework :: Django
Classifier: Intended Audience :: Developers
Classifier: License :: OSI Approved :: MIT License
Classifier: Operating System :: OS Independent
Classifier: Programming Language :: Python
Classifier: Programming Language :: Python
Classifier: Programming Language :: Python :: 2.6
Classifier: Programming Language :: Python :: 2.7
